thor_devkit/__init__.py
thor_devkit/abi.py
thor_devkit/bloom.py
thor_devkit/certificate.py
thor_devkit/rlp.py
thor_devkit/transaction.py
thor_devkit/cry/__init__.py
thor_devkit/cry/address.py
thor_devkit/cry/blake2b.py
thor_devkit/cry/hdnode.py
thor_devkit/cry/keccak.py
thor_devkit/cry/keystore.py
thor_devkit/cry/mnemonic.py
thor_devkit/cry/secp256k1.py
thor_devkit/cry/utils.py
thor_devkit-1.0.14.dist-info/LICENSE
thor_devkit-1.0.14.dist-info/METADATA
thor_devkit-1.0.14.dist-info/WHEEL
thor_devkit-1.0.14.dist-info/top_level.txt
thor_devkit-1.0.14.dist-info/RECORD
