Metadata-Version: 2.1
Name: thor-devkit
Version: 1.0.14
Summary: SDK to interact with VeChain Thor public blockchain.
Home-page: https://github.com/laalaguer/thor-devkit.py
Author: A Byte Ahead
Author-email: laalaguer@gmail.com
License: UNKNOWN
Project-URL: Documentation, https://github.com/laalaguer/thor-devkit.py
Project-URL: Source, https://github.com/laalaguer/thor-devkit.py
Project-URL: Issue Tracker, https://github.com/laalaguer/thor-devkit.py/issues
Keywords: vechain thor blockchain sdk
Platform: UNKNOWN
Classifier: Programming Language :: Python :: 3
Classifier: Intended Audience :: Developers
Classifier: Topic :: Software Development :: Build Tools
Classifier: License :: OSI Approved :: GNU General Public License v3 (GPLv3)
Classifier: Operating System :: OS Independent
Requires-Python: >=3.6
License-File: LICENSE
Requires-Dist: eth-hash (==0.5.2)
Requires-Dist: pytest (>=6.2.0)
Requires-Dist: pytest-cov
Requires-Dist: ecdsa (==0.16.1)
Requires-Dist: eth-keys (==0.3.3)
Requires-Dist: mnemonic (==0.19)
Requires-Dist: retro-bip-utils (==1.0.5)
Requires-Dist: eth-keyfile (==0.5.1)
Requires-Dist: rlp (==1.2.0)
Requires-Dist: eth-abi (==2.1.1)
Requires-Dist: voluptuous (==0.12.0)
Requires-Dist: wheel
Requires-Dist: twine
